x86cpu/__init__.py
x86cpu/_version.py
x86cpu/cpuinfo.pyd
x86cpu/tests/info_getters.py
x86cpu/tests/test_cpuinfo.py
x86cpu-0.4.dist-info/DESCRIPTION.rst
x86cpu-0.4.dist-info/METADATA
x86cpu-0.4.dist-info/RECORD
x86cpu-0.4.dist-info/WHEEL
x86cpu-0.4.dist-info/entry_points.txt
x86cpu-0.4.dist-info/metadata.json
x86cpu-0.4.dist-info/top_level.txt
