Metadata-Version: 1.1
Name: x86cpu
Version: 0.4
Summary: Collect information about x86 CPU
Home-page: http://github.com/matthew-brett/x86cpu
Author: Matthew Brett
Author-email: matthew.brett@gmail.com
License: BSD license
Platform: UNKNOWN
Classifier: Development Status :: 2 - Pre-Alpha
Classifier: Environment :: Console
Classifier: Intended Audience :: Developers
Classifier: License :: OSI Approved :: BSD License
Classifier: Programming Language :: Python
Classifier: Programming Language :: Python :: 3
Classifier: Operating System :: Microsoft :: Windows
Classifier: Operating System :: POSIX
Classifier: Operating System :: Unix
Classifier: Operating System :: MacOS
